{
  "url": "http://127.0.0.1:5000",
  "names":
  {
    "": "home",
    "competitions": "competitions",
    "algorithms": "algorithms",
    "lectures": "lectures",
    "tips": "weekly tips",
    "history": "history",
    "contact": "contact",
    "eligibility": "eligibility",
    "admission": "admission of openness",
    "vote": "vote!",
    "run": "run for office",
    "result": "result",
    "search": "search"
  },
  "order": ["", "competitions", "algorithms", "lectures", "history", "contact", ["archive", ["tips"]], ["vote", ["eligibility", "admission", "vote", "run", "result"]]]
}
